google/cloud/enterpriseknowledgegraph/__init__.py
google/cloud/enterpriseknowledgegraph/gapic_version.py
google/cloud/enterpriseknowledgegraph/py.typed
google/cloud/enterpriseknowledgegraph_v1/__init__.py
google/cloud/enterpriseknowledgegraph_v1/gapic_metadata.json
google/cloud/enterpriseknowledgegraph_v1/gapic_version.py
google/cloud/enterpriseknowledgegraph_v1/py.typed
google/cloud/enterpriseknowledgegraph_v1/services/__init__.py
google/cloud/enterpriseknowledgegraph_v1/services/enterprise_knowledge_graph_service/__init__.py
google/cloud/enterpriseknowledgegraph_v1/services/enterprise_knowledge_graph_service/async_client.py
google/cloud/enterpriseknowledgegraph_v1/services/enterprise_knowledge_graph_service/client.py
google/cloud/enterpriseknowledgegraph_v1/services/enterprise_knowledge_graph_service/pagers.py
google/cloud/enterpriseknowledgegraph_v1/services/enterprise_knowledge_graph_service/transports/__init__.py
google/cloud/enterpriseknowledgegraph_v1/services/enterprise_knowledge_graph_service/transports/base.py
google/cloud/enterpriseknowledgegraph_v1/services/enterprise_knowledge_graph_service/transports/grpc.py
google/cloud/enterpriseknowledgegraph_v1/services/enterprise_knowledge_graph_service/transports/grpc_asyncio.py
google/cloud/enterpriseknowledgegraph_v1/services/enterprise_knowledge_graph_service/transports/rest.py
google/cloud/enterpriseknowledgegraph_v1/services/enterprise_knowledge_graph_service/transports/rest_base.py
google/cloud/enterpriseknowledgegraph_v1/types/__init__.py
google/cloud/enterpriseknowledgegraph_v1/types/job_state.py
google/cloud/enterpriseknowledgegraph_v1/types/operation_metadata.py
google/cloud/enterpriseknowledgegraph_v1/types/service.py
google_cloud_enterpriseknowledgegraph-0.4.0.dist-info/licenses/LICENSE
google_cloud_enterpriseknowledgegraph-0.4.0.dist-info/METADATA
google_cloud_enterpriseknowledgegraph-0.4.0.dist-info/WHEEL
google_cloud_enterpriseknowledgegraph-0.4.0.dist-info/top_level.txt
google_cloud_enterpriseknowledgegraph-0.4.0.dist-info/RECORD
